grapetree/GT_icon.icns
grapetree/GT_icon.ico
grapetree/LICENSE
grapetree/MSTree_holder.html
grapetree/README.md
grapetree/__init__.py
grapetree/grapetree.py
grapetree/simulation_generate.py
grapetree/simulation_getTrees.py
grapetree/binaries/Ninja.jar
grapetree/binaries/edmonds-linux
grapetree/binaries/edmonds-osx
grapetree/binaries/edmonds.exe
grapetree/binaries/fastme-2.1.5-linux32
grapetree/binaries/fastme-2.1.5-linux64
grapetree/binaries/fastme-2.1.5-osx
grapetree/binaries/fastme.exe
grapetree/binaries/rapidnj
grapetree/binaries/rapidnj-osx
grapetree/binaries/rapidnj.exe
grapetree/module/MSTrees.py
grapetree/module/MSTrees.pyc
grapetree/module/MSTrees2.py
grapetree/module/__init__.py
grapetree/module/__init__.pyc
grapetree/module/config.py
grapetree/module/config.pyc
grapetree/module/countries.csv
grapetree/module/geocode.py
grapetree/module/geocode.pyc
grapetree/module/views.py
grapetree/module/views.pyc
grapetree/static/css/bootstrap.min.css
grapetree/static/css/grapetree.css
grapetree/static/fonts/glyphicons-halflings-regular.woff
grapetree/static/fonts/glyphicons-halflings-regular.woff2
grapetree/static/js/bootstrap-theme.css
grapetree/static/js/controls.js
grapetree/static/js/SlickGrid/MIT-LICENSE.txt
grapetree/static/js/SlickGrid/README.md
grapetree/static/js/SlickGrid/index.js
grapetree/static/js/SlickGrid/package.json
grapetree/static/js/SlickGrid/slick-default-theme.css
grapetree/static/js/SlickGrid/slick.core.js
grapetree/static/js/SlickGrid/slick.dataview.js
grapetree/static/js/SlickGrid/slick.editors.js
grapetree/static/js/SlickGrid/slick.formatters.js
grapetree/static/js/SlickGrid/slick.grid.css
grapetree/static/js/SlickGrid/slick.grid.js
grapetree/static/js/SlickGrid/slick.groupitemmetadataprovider.js
grapetree/static/js/SlickGrid/slick.remotemodel-yahoo.js
grapetree/static/js/SlickGrid/slick.remotemodel.js
grapetree/static/js/SlickGrid/controls/slick.columnpicker.css
grapetree/static/js/SlickGrid/controls/slick.columnpicker.js
grapetree-2.2.dist-info/LICENSE
grapetree-2.2.dist-info/METADATA
grapetree-2.2.dist-info/WHEEL
grapetree-2.2.dist-info/entry_points.txt
grapetree-2.2.dist-info/top_level.txt
grapetree-2.2.dist-info/RECORD
