Metadata-Version: 2.1
Name: grapetree
Version: 2.2
Summary: Web interface of GrapeTree, which is a program for phylogenetic analysis.
Home-page: https://github.com/achtman-lab/GrapeTree
Author: EnteroBase development team
Author-email: zhemin.zhou@warwick.ac.uk
License: UNKNOWN
Project-URL: Bug Reports, https://github.com/achtman-lab/GrapeTree/issues
Project-URL: Source, https://github.com/achtman-lab/GrapeTree
Keywords: bioinformatics,microbial,genomics,MLST,visulisation
Platform: UNKNOWN
Classifier: Development Status :: 5 - Production/Stable
Classifier: License :: OSI Approved :: GNU General Public License v3 (GPLv3)
Classifier: Programming Language :: Python :: 3.5
Classifier: Programming Language :: Python :: 3.6
Classifier: Programming Language :: Python :: 3.7
Classifier: Programming Language :: Python :: 3.8
Requires-Dist: ete3
Requires-Dist: numpy
Requires-Dist: Flask
Requires-Dist: networkx
Requires-Dist: psutil
Requires-Dist: numba
Requires-Dist: unidecode
